ARCIMBOLDO_FULL/ADT.py
ARCIMBOLDO_FULL/ALIXE.py
ARCIMBOLDO_FULL/ANOMLIB.py
ARCIMBOLDO_FULL/ARCIMBOLDO_BORGES.py
ARCIMBOLDO_FULL/ARCIMBOLDO_LITE.py
ARCIMBOLDO_FULL/ARCIMBOLDO_SHREDDER.py
ARCIMBOLDO_FULL/Data.py
ARCIMBOLDO_FULL/FFT.py
ARCIMBOLDO_FULL/LibSLIDER.py
ARCIMBOLDO_FULL/Quaternions.py
ARCIMBOLDO_FULL/SELSLIB2.py
ARCIMBOLDO_FULL/SLIDER.py
ARCIMBOLDO_FULL/SPACE_GROUPS.py
ARCIMBOLDO_FULL/__init__.py
ARCIMBOLDO_FULL/alixe_library.py
ARCIMBOLDO_FULL/arci_output.py
ARCIMBOLDO_FULL/setup_example.bor
ARCIMBOLDO_FULL/unitCellTools.py
ARCIMBOLDO_FULL/ALEPH/__init__.py
ARCIMBOLDO_FULL/ALEPH/setup.py
ARCIMBOLDO_FULL/ALEPH/aleph/__init__.py
ARCIMBOLDO_FULL/ALEPH/aleph/core/ALEPH.py
ARCIMBOLDO_FULL/ALEPH/aleph/core/Bioinformatics.py
ARCIMBOLDO_FULL/ALEPH/aleph/core/Grid.py
ARCIMBOLDO_FULL/ALEPH/aleph/core/SystemUtility.py
ARCIMBOLDO_FULL/ALEPH/aleph/core/__init__.py
ARCIMBOLDO_FULL/ALEPH/aleph/core/managerSSH.py
ARCIMBOLDO_FULL/executables/chescat_linux
ARCIMBOLDO_FULL/executables/chescat_mac
ARCIMBOLDO_FULL/executables/spack_linux
ARCIMBOLDO_FULL/executables/spack_mac
ARCIMBOLDO_FULL/executables/sprout_linux
ARCIMBOLDO_FULL/executables/sprout_mac
ARCIMBOLDO_FULL/mattprob_data_tables_2013/pdb_02_06_2013_mix_sorted_flagged_highest_cs.json
ARCIMBOLDO_FULL/mattprob_data_tables_2013/pdb_02_06_2013_nuc_sorted_flagged_highest_cs.json
ARCIMBOLDO_FULL/mattprob_data_tables_2013/pdb_02_06_2013_pro_sorted_flagged_highest_cs.json
arcimboldo-1.0.25.dist-info/LICENSE
arcimboldo-1.0.25.dist-info/METADATA
arcimboldo-1.0.25.dist-info/WHEEL
arcimboldo-1.0.25.dist-info/entry_points.txt
arcimboldo-1.0.25.dist-info/top_level.txt
arcimboldo-1.0.25.dist-info/RECORD
